graphgen/__init__.py
graphgen/data/__init__.py
graphgen/data/data.py
graphgen/data/utils.py
graphgen/generate/__init__.py
graphgen/generate/generate.py
graphgen/generate/utils.py
graphgen/graph/__init__.py
graphgen/graph/graph.py
graphgen/graph/node.py
graphgen/graph/utils.py
graphgen/metric/__init__.py
graphgen/metric/metric.py
graphgen-0.0.7.dist-info/LICENSE
graphgen-0.0.7.dist-info/METADATA
graphgen-0.0.7.dist-info/WHEEL
graphgen-0.0.7.dist-info/top_level.txt
graphgen-0.0.7.dist-info/RECORD
