Metadata-Version: 2.1
Name: graphgen
Version: 0.0.7
Summary: A package to generate graphs from GPS data
Home-page: https://github.com/bhaveshk658/graphgen
Author: Bhavesh Kalisetti
Author-email: bhaveshk658@berkeley.edu
License: UNKNOWN
Platform: UNKNOWN
Classifier: Programming Language :: Python :: 3
Classifier: License :: OSI Approved :: MIT License
Classifier: Operating System :: OS Independent
Requires-Python: >=3.6
